aliyundriveAutoCheckin/__init__.py
aliyundriveAutoCheckin/aliyundriveAutoCheckin.py
aliyundriveAutoCheckin-1.7.dist-info/METADATA
aliyundriveAutoCheckin-1.7.dist-info/WHEEL
aliyundriveAutoCheckin-1.7.dist-info/top_level.txt
aliyundriveAutoCheckin-1.7.dist-info/RECORD
