Metadata-Version: 2.1
Name: aliyundriveAutoCheckin
Version: 1.7
Author: xiaohan17
Author-email: 2799153122@qq.com
Requires-Dist: requests
